{
    "keep": {
        "days": true,
        "amount": 7
    },
    "auditLog": "C:\\Leather for Luxury\\logs\\winston\\successes\\.c7eb9931edbcd1cdaae3751367885eab829daa69-audit.json",
    "files": [
        {
            "date": 1732048368917,
            "name": "C:\\Leather for Luxury\\logs\\winston\\successes\\leather-2024-20-11-02-success.log",
            "hash": "573deee8c42bab15023230bf28df0630376fad66232c5609a3017c2dfb408acf"
        },
        {
            "date": 1732050385779,
            "name": "C:\\Leather for Luxury\\logs\\winston\\successes\\leather-2024-20-11-03-success.log",
            "hash": "486799b4936205b2bff985abea288bdb20450c48c4abcb6fbeed697b8c15dadc"
        },
        {
            "date": 1732055111666,
            "name": "C:\\Leather for Luxury\\logs\\winston\\successes\\leather-2024-20-11-04-success.log",
            "hash": "8bfc2eb9540298efa92b2c120bf0f82748dc90d69019528247550b705cd6abdf"
        },
        {
            "date": 1732057350909,
            "name": "C:\\Leather for Luxury\\logs\\winston\\successes\\leather-2024-20-11-05-success.log",
            "hash": "a019efbcf999bd0e2b032fb092793c3861d30d9030f7bd0d94274f2dc9b0da4f"
        },
        {
            "date": 1732128640503,
            "name": "C:\\Leather for Luxury\\logs\\winston\\successes\\leather-2024-21-11-00-success.log",
            "hash": "c5edd33496a17815bd95c5cc0e434f11ed2bef55ca606a54d2189e399cd41424"
        },
        {
            "date": 1732129470146,
            "name": "C:\\Leather for Luxury\\logs\\winston\\successes\\leather-2024-21-11-01-success.log",
            "hash": "91f22aa3d9e299d06000ecf8dc6f42dc8fea79313a65a964a256bfe5efad9484"
        },
        {
            "date": 1732132810517,
            "name": "C:\\Leather for Luxury\\logs\\winston\\successes\\leather-2024-21-11-02-success.log",
            "hash": "40eb53f78b6f4f539aa4d4329c85a17aca67fb8315c1b6bdb50618b936db7d71"
        }
    ],
    "hashType": "sha256"
}